{
  "attrs": {
    "reduce_alloc": {
      "h": [
        [
          0,
          1,
          1,
          1,
          1,
          0
        ]
      ],
      "v": [
        [
          1,
          2,
          2
        ],
        [
          0,
          2,
          2
        ]
      ]
    }
  },
  "paths": [
    {
      "hide": false,
      "points": [
        [
          1,
          1
        ],
        [
          1,
          0
        ]
      ]
    },
    {
      "hide": false,
      "points": [
        [
          3,
          0
        ],
        [
          3,
          3
        ]
      ]
    },
    {
      "hide": false,
      "points": [
        [
          5,
          1
        ],
        [
          5,
          0
        ]
      ]
    },
    {
      "hide": false,
      "points": [
        [
          0,
          3
        ],
        [
          6,
          3
        ]
      ]
    },
    {
      "hide": false,
      "points": [
        [
          2,
          3
        ],
        [
          2,
          6
        ],
        [
          0,
          6
        ]
      ]
    },
    {
      "hide": false,
      "points": [
        [
          4,
          3
        ],
        [
          4,
          6
        ],
        [
          6,
          6
        ]
      ]
    }
  ]
}