{
  "attrs": {
    "preset_center": {
      "v": 0.5
    },
    "reduce_alloc": {
      "h": [
        [
          0,
          2,
          2,
          0
        ]
      ],
      "v": [
        [
          2,
          2,
          1
        ]
      ]
    }
  },
  "paths": [
    {
      "hide": false,
      "points": [
        [
          0,
          0
        ],
        [
          6,
          0
        ]
      ]
    },
    {
      "hide": false,
      "points": [
        [
          0,
          4
        ],
        [
          6,
          4
        ]
      ]
    },
    {
      "hide": false,
      "points": [
        [
          3,
          0
        ],
        [
          3,
          6
        ]
      ]
    },
    {
      "hide": false,
      "points": [
        [
          0,
          2
        ],
        [
          1,
          2
        ]
      ]
    },
    {
      "hide": false,
      "points": [
        [
          6,
          2
        ],
        [
          5,
          2
        ]
      ]
    }
  ]
}